setup.cfg
setup.py
ryanwinterstest1221/__init__.py
ryanwinterstest1221.egg-info/PKG-INFO
ryanwinterstest1221.egg-info/SOURCES.txt
ryanwinterstest1221.egg-info/dependency_links.txt
ryanwinterstest1221.egg-info/not-zip-safe
ryanwinterstest1221.egg-info/top_level.txt