Metadata-Version: 1.0
Name: ryanwinterstest1221
Version: 0.1
Summary: This is just a test, go away
Home-page: https://github.com/ryanwintersusc
Author: Ryan Winters
Author-email: ryanwint@usc.edu
License: MIT
Platform: UNKNOWN
